openspeleo_lib/__init__.py
openspeleo_lib/constants.py
openspeleo_lib/debug_utils.py
openspeleo_lib/enums.py
openspeleo_lib/errors.py
openspeleo_lib/generators.py
openspeleo_lib/geo_utils.py
openspeleo_lib/geojson.py
openspeleo_lib/logger.py
openspeleo_lib/models.py
openspeleo_lib/pydantic_utils.py
openspeleo_lib/utils.py
openspeleo_lib/commands/__init__.py
openspeleo_lib/commands/convert.py
openspeleo_lib/commands/encrypt.py
openspeleo_lib/commands/main.py
openspeleo_lib/commands/validate_tml.py
openspeleo_lib/interfaces/__init__.py
openspeleo_lib/interfaces/base.py
openspeleo_lib/interfaces/ariane/__init__.py
openspeleo_lib/interfaces/ariane/decoding.py
openspeleo_lib/interfaces/ariane/encoding.py
openspeleo_lib/interfaces/ariane/enums_cls.py
openspeleo_lib/interfaces/ariane/interface.py
openspeleo_lib/interfaces/ariane/name_map.py
openspeleo_lib/interfaces/ariane/xml_utils.py
openspeleo_lib-0.0.13.dist-info/entry_points.txt
openspeleo_lib-0.0.13.dist-info/licenses/LICENSE
openspeleo_lib-0.0.13.dist-info/WHEEL
openspeleo_lib-0.0.13.dist-info/METADATA
openspeleo_lib-0.0.13.dist-info/RECORD
